gira/__init__.py
gira/constants.py
gira/py.typed
gira/api/__init__.py
gira/api/async_ops/__init__.py
gira/api/async_ops/cancellation.py
gira/api/async_ops/manager.py
gira/api/async_ops/persistence.py
gira/api/async_ops/progress.py
gira/api/async_ops/streaming.py
gira/api/bulk/__init__.py
gira/api/bulk/dependencies.py
gira/api/bulk/errors.py
gira/api/bulk/manager.py
gira/api/bulk/response.py
gira/api/bulk/schemas.py
gira/api/bulk/tracker.py
gira/api/bulk/update.py
gira/api/bulk/validation.py
gira/cli/__init__.py
gira/cli/main.py
gira/cli/commands/__init__.py
gira/cli/commands/ai.py
gira/cli/commands/backlog.py
gira/cli/commands/backup.py
gira/cli/commands/board.py
gira/cli/commands/cache.py
gira/cli/commands/completion.py
gira/cli/commands/config.py
gira/cli/commands/context.py
gira/cli/commands/describe.py
gira/cli/commands/extensibility_hooks.py
gira/cli/commands/graph.py
gira/cli/commands/init.py
gira/cli/commands/operation.py
gira/cli/commands/query.py
gira/cli/commands/query_list.py
gira/cli/commands/query_run.py
gira/cli/commands/query_save.py
gira/cli/commands/sync.py
gira/cli/commands/workflow.py
gira/cli/commands/archive/__init__.py
gira/cli/commands/archive/archive_done.py
gira/cli/commands/archive/archive_old.py
gira/cli/commands/archive/archive_ticket.py
gira/cli/commands/archive/list.py
gira/cli/commands/archive/restore.py
gira/cli/commands/archive/suggest.py
gira/cli/commands/attachment/__init__.py
gira/cli/commands/attachment/add.py
gira/cli/commands/attachment/add_original.py
gira/cli/commands/attachment/cat.py
gira/cli/commands/attachment/download.py
gira/cli/commands/attachment/list.py
gira/cli/commands/attachment/open.py
gira/cli/commands/attachment/remove.py
gira/cli/commands/comment/__init__.py
gira/cli/commands/comment/add.py
gira/cli/commands/comment/attach.py
gira/cli/commands/comment/delete.py
gira/cli/commands/comment/delete_inline.py
gira/cli/commands/comment/detach.py
gira/cli/commands/comment/download.py
gira/cli/commands/comment/list.py
gira-0.2.2.dist-info/licenses/LICENSE
gira-0.2.2.dist-info/METADATA
gira-0.2.2.dist-info/WHEEL
gira-0.2.2.dist-info/entry_points.txt
gira-0.2.2.dist-info/top_level.txt
gira-0.2.2.dist-info/RECORD
