Metadata-Version: 2.4
Name: gira
Version: 0.2.2
Summary: Git-based project management for developers and AI agents
Author-email: GoatBytes <contact@goatbytes.dev>
Maintainer-email: Jared Rummler <jared@goatbytes.dev>
License: MIT
Project-URL: Homepage, https://github.com/goatbytes/gira
Project-URL: Documentation, https://github.com/goatbytes/gira/tree/main/docs
Project-URL: Repository, https://github.com/goatbytes/gira.git
Project-URL: Issues, https://github.com/goatbytes/gira/issues
Keywords: project-management,git,cli,agile,tickets,ai-agents
Classifier: Development Status :: 3 - Alpha
Classifier: Intended Audience :: Developers
Classifier: Topic :: Software Development :: Bug Tracking
Classifier: Topic :: Software Development :: Version Control :: Git
Classifier: License :: OSI Approved :: MIT License
Classifier: Programming Language :: Python :: 3
Classifier: Programming Language :: Python :: 3.8
Classifier: Programming Language :: Python :: 3.9
Classifier: Programming Language :: Python :: 3.10
Classifier: Programming Language :: Python :: 3.11
Classifier: Programming Language :: Python :: 3.12
Classifier: Environment :: Console
Classifier: Operating System :: OS Independent
Requires-Python: >=3.8
License-File: LICENSE
Requires-Dist: typer>=0.16.0
Requires-Dist: pydantic>=2.11.7
Requires-Dist: pydantic[email]>=2.11.7
Requires-Dist: pydantic-settings>=2.0.0
Requires-Dist: rich>=14.0.0
Requires-Dist: GitPython>=3.1.45
Requires-Dist: jsonpath-ng>=1.6.0
Requires-Dist: Jinja2>=3.1.0
Requires-Dist: cryptography>=45.0.5
Requires-Dist: urllib3>=2.0.0
Requires-Dist: pytz>=2024.1
Requires-Dist: fastmcp>=1.0.0
Requires-Dist: python-dotenv>=1.0.0
Provides-Extra: dev
Requires-Dist: pytest>=8.4.1; extra == "dev"
Requires-Dist: pytest-cov>=5.0.0; extra == "dev"
Requires-Dist: pytest-mock>=3.14.0; extra == "dev"
Requires-Dist: pytest-asyncio>=0.23.6; extra == "dev"
Requires-Dist: pytest-timeout>=2.3.1; extra == "dev"
Requires-Dist: pytest-xdist>=3.5.0; extra == "dev"
Requires-Dist: black>=25.1.0; extra == "dev"
Requires-Dist: ruff>=0.4.4; extra == "dev"
Requires-Dist: mypy>=1.16.1; extra == "dev"
Requires-Dist: pre-commit>=3.7.1; extra == "dev"
Requires-Dist: faker>=25.2.0; extra == "dev"
Requires-Dist: freezegun>=1.4.0; extra == "dev"
Requires-Dist: hypothesis>=6.100.0; extra == "dev"
Requires-Dist: pyfakefs>=5.5.0; extra == "dev"
Provides-Extra: gcs
Requires-Dist: google-cloud-storage>=3.2.0; extra == "gcs"
Provides-Extra: azure
Requires-Dist: azure-storage-blob>=12.26.0; extra == "azure"
Requires-Dist: azure-identity>=1.23.1; extra == "azure"
Provides-Extra: s3
Requires-Dist: boto3>=1.34.0; extra == "s3"
Provides-Extra: docs
Requires-Dist: mkdocs-material>=9.5.0; extra == "docs"
Requires-Dist: mkdocs-gen-files>=0.5.0; extra == "docs"
Requires-Dist: mkdocstrings[python]>=0.24.0; extra == "docs"
Requires-Dist: pymdown-extensions>=10.7.0; extra == "docs"
Requires-Dist: mkdocs-glightbox>=0.3.4; extra == "docs"
Requires-Dist: mkdocs-git-authors-plugin>=0.7.2; extra == "docs"
Requires-Dist: mkdocs-mermaid2-plugin>=1.1.1; extra == "docs"
Requires-Dist: mkdocs-rss-plugin>=1.12.2; extra == "docs"
Requires-Dist: mkdocs-charts-plugin>=0.0.10; extra == "docs"
Requires-Dist: mkdocs-diagrams>=1.0.0; extra == "docs"
Dynamic: license-file
